bb2parse/BloodBowlMatch.py
bb2parse/BloodBowlSeason.py
bb2parse/__init__.py
bb2parse/example.py
bb2parse/parse.py
bb2parse-1.0.0.dist-info/LICENSE
bb2parse-1.0.0.dist-info/METADATA
bb2parse-1.0.0.dist-info/WHEEL
bb2parse-1.0.0.dist-info/top_level.txt
bb2parse-1.0.0.dist-info/RECORD
