Metadata-Version: 2.1
Name: bb2parse
Version: 1.0.0
Summary: Python wrapper for BloodBowl Match files
Home-page: https://github.com/CarsenKennedy/bb2parse
Author: Carsen Kennedy
Author-email: carsenkennedy@pm.me
License: MIT
Platform: UNKNOWN
Requires-Dist: ordered-set
